cli/__init__.py
cli/main.py
cli/pmcli.py
productmap_cli-0.1.25.dist-info/METADATA
productmap_cli-0.1.25.dist-info/WHEEL
productmap_cli-0.1.25.dist-info/entry_points.txt
productmap_cli-0.1.25.dist-info/top_level.txt
productmap_cli-0.1.25.dist-info/RECORD
