Metadata-Version: 2.4
Name: productmap-cli
Version: 0.1.25
Summary: The ProductMap CLI tool for validation and execution of map generation process in the ProductMap tool
Author-email: ProductMap <axel.reichwein@koneksys.com>
Maintainer-email: ProductMap <axel.reichwein@koneksys.com>
Classifier: Programming Language :: Python :: 3.12
Requires-Python: >=3.12
Requires-Dist: click
Requires-Dist: httpx
